iagent/__init__.py
iagent/agents.py
iagent/cli.py
iagent/executor.py
iagent/memory.py
iagent/models.py
iagent/system_monitor.py
iagent/tools.py
iagent/utils.py
iagent/cicd_debugger/__init__.py
iagent/cicd_debugger/cli.py
iagent/cicd_debugger/debugger.py
iagent/cicd_debugger/fetch_logs.py
iagent/cicd_debugger/monitor.py
iagent/cicd_debugger/notifier.py
iagent/cicd_debugger/parser.py
iagent/cicd_debugger/pr_generator.py
iagent/cicd_debugger/suggest_fix.py
iagent/cicd_debugger/tools.py
iagent/cicd_debugger/wrapper.py
iagent/tools/system_monitor.py
ideaweaver_agent-0.0.1.post1.dist-info/METADATA
ideaweaver_agent-0.0.1.post1.dist-info/WHEEL
ideaweaver_agent-0.0.1.post1.dist-info/entry_points.txt
ideaweaver_agent-0.0.1.post1.dist-info/top_level.txt
ideaweaver_agent-0.0.1.post1.dist-info/RECORD
