Metadata-Version: 2.4
Name: ideaweaver-agent
Version: 0.0.1.post1
Summary: 🤖 iagent: Intelligent Agents that Think in Code
Home-page: https://github.com/your-username/iagent
Author: Prashant Lakhera
Author-email: Prashant Lakhera <plakhera@ideaweaver.ai>
Maintainer-email: Prashant Lakhera <plakhera@ideaweaver.ai>
License-Expression: Apache-2.0
Project-URL: Homepage, https://github.com/plakhera/iagent
Project-URL: Repository, https://github.com/plakhera/iagent
Project-URL: Documentation, https://github.com/plakhera/iagent#readme
Project-URL: Issues, https://github.com/plakhera/iagent/issues
Keywords: ai,agents,llm,code-execution,automation
Classifier: Development Status :: 4 - Beta
Classifier: Intended Audience :: Developers
Classifier: Operating System :: OS Independent
Classifier: Programming Language :: Python :: 3
Classifier: Programming Language :: Python :: 3.10
Classifier: Programming Language :: Python :: 3.11
Classifier: Programming Language :: Python :: 3.12
Classifier: Topic :: Scientific/Engineering :: Artificial Intelligence
Classifier: Topic :: Software Development :: Libraries :: Python Modules
Requires-Python: >=3.10
Requires-Dist: huggingface-hub>=0.31.2
Requires-Dist: requests>=2.32.3
Requires-Dist: rich>=13.9.4
Requires-Dist: jinja2>=3.1.4
Requires-Dist: python-dotenv
Requires-Dist: openai>=1.58.1
Requires-Dist: litellm>=1.60.2
Requires-Dist: pandas>=1.3.0
Requires-Dist: python-dateutil>=2.8.0
Provides-Extra: torch
Requires-Dist: torch; extra == "torch"
Requires-Dist: transformers>=4.0.0; extra == "torch"
Requires-Dist: accelerate; extra == "torch"
Provides-Extra: gradio
Requires-Dist: gradio>=5.14.0; extra == "gradio"
Provides-Extra: all
Requires-Dist: iagent[gradio,torch]; extra == "all"
Dynamic: author
Dynamic: home-page
Dynamic: requires-python
